{
  "ruta": "bosque_verde",
  "zona": "Zonas_Verdes",
  "encuentros": {
    "10": {
      "id": 10,
      "encuentros_fase": 0,
      "shinies": 0,
      "huidos": 0,
      "encuentros_totales": 0,
      "iv_record": {
        "max": -1,
        "min": -1
      },
      "sv_record": {
        "max": -1,
        "min": -1
      }
    },
    "11": {
      "id": 11,
      "encuentros_fase": 0,
      "shinies": 0,
      "huidos": 0,
      "encuentros_totales": 0,
      "iv_record": {
        "max": -1,
        "min": -1
      },
      "sv_record": {
        "max": -1,
        "min": -1
      }
    },
    "16": {
      "id": 16,
      "encuentros_fase": 0,
      "shinies": 0,
      "huidos": 0,
      "encuentros_totales": 0,
      "iv_record": {
        "max": -1,
        "min": -1
      },
      "sv_record": {
        "max": -1,
        "min": -1
      }
    },
    "17": {
      "id": 17,
      "encuentros_fase": 0,
      "shinies": 0,
      "huidos": 0,
      "encuentros_totales": 0,
      "iv_record": {
        "max": -1,
        "min": -1
      },
      "sv_record": {
        "max": -1,
        "min": -1
      }
    },
    "25": {
      "id": 25,
      "encuentros_fase": 0,
      "shinies": 0,
      "huidos": 0,
      "encuentros_totales": 0,
      "iv_record": {
        "max": -1,
        "min": -1
      },
      "sv_record": {
        "max": -1,
        "min": -1
      }
    },
    "12": {
      "id": 12,
      "encuentros_fase": 0,
      "shinies": 0,
      "huidos": 0,
      "encuentros_totales": 0,
      "iv_record": {
        "max": -1,
        "min": -1
      },
      "sv_record": {
        "max": -1,
        "min": -1
      }
    },
    "163": {
      "id": 163,
      "encuentros_fase": 0,
      "shinies": 0,
      "huidos": 0,
      "encuentros_totales": 0,
      "iv_record": {
        "max": -1,
        "min": -1
      },
      "sv_record": {
        "max": -1,
        "min": -1
      }
    },
    "164": {
      "id": 164,
      "encuentros_fase": 0,
      "shinies": 0,
      "huidos": 0,
      "encuentros_totales": 0,
      "iv_record": {
        "max": -1,
        "min": -1
      },
      "sv_record": {
        "max": -1,
        "min": -1
      }
    },
    "322": {
      "id": 322,
      "encuentros_fase": 0,
      "shinies": 0,
      "huidos": 0,
      "encuentros_totales": 0,
      "iv_record": {
        "max": -1,
        "min": -1
      },
      "sv_record": {
        "max": -1,
        "min": -1
      }
    },
    "325": {
      "id": 325,
      "encuentros_fase": 0,
      "shinies": 0,
      "huidos": 0,
      "encuentros_totales": 0,
      "iv_record": {
        "max": -1,
        "min": -1
      },
      "sv_record": {
        "max": -1,
        "min": -1
      }
    },
    "406": {
      "id": 406,
      "encuentros_fase": 0,
      "shinies": 0,
      "huidos": 0,
      "encuentros_totales": 0,
      "iv_record": {
        "max": -1,
        "min": -1
      },
      "sv_record": {
        "max": -1,
        "min": -1
      }
    },
    "455": {
      "id": 455,
      "encuentros_fase": 0,
      "shinies": 0,
      "huidos": 0,
      "encuentros_totales": 0,
      "iv_record": {
        "max": -1,
        "min": -1
      },
      "sv_record": {
        "max": -1,
        "min": -1
      }
    },
    "401": {
      "id": 401,
      "encuentros_fase": 0,
      "shinies": 0,
      "huidos": 0,
      "encuentros_totales": 0,
      "iv_record": {
        "max": -1,
        "min": -1
      },
      "sv_record": {
        "max": -1,
        "min": -1
      }
    }
  }
}