{
  "ruta": "cataratas_tohjo",
  "zona": "Zonas_Verdes",
  "encuentros": {
    "20": {
      "id": 20,
      "encuentros_fase": 0,
      "shinies": 0,
      "huidos": 0,
      "encuentros_totales": 0,
      "iv_record": {
        "max": -1,
        "min": -1
      },
      "sv_record": {
        "max": -1,
        "min": -1
      }
    },
    "41": {
      "id": 41,
      "encuentros_fase": 0,
      "shinies": 0,
      "huidos": 0,
      "encuentros_totales": 0,
      "iv_record": {
        "max": -1,
        "min": -1
      },
      "sv_record": {
        "max": -1,
        "min": -1
      }
    },
    "79": {
      "id": 79,
      "encuentros_fase": 0,
      "shinies": 0,
      "huidos": 0,
      "encuentros_totales": 0,
      "iv_record": {
        "max": -1,
        "min": -1
      },
      "sv_record": {
        "max": -1,
        "min": -1
      }
    },
    "19": {
      "id": 19,
      "encuentros_fase": 0,
      "shinies": 0,
      "huidos": 0,
      "encuentros_totales": 0,
      "iv_record": {
        "max": -1,
        "min": -1
      },
      "sv_record": {
        "max": -1,
        "min": -1
      }
    },
    "42": {
      "id": 42,
      "encuentros_fase": 0,
      "shinies": 0,
      "huidos": 0,
      "encuentros_totales": 0,
      "iv_record": {
        "max": -1,
        "min": -1
      },
      "sv_record": {
        "max": -1,
        "min": -1
      }
    },
    "296": {
      "id": 296,
      "encuentros_fase": 0,
      "shinies": 0,
      "huidos": 0,
      "encuentros_totales": 0,
      "iv_record": {
        "max": -1,
        "min": -1
      },
      "sv_record": {
        "max": -1,
        "min": -1
      }
    },
    "359": {
      "id": 359,
      "encuentros_fase": 0,
      "shinies": 0,
      "huidos": 0,
      "encuentros_totales": 0,
      "iv_record": {
        "max": -1,
        "min": -1
      },
      "sv_record": {
        "max": -1,
        "min": -1
      }
    },
    "433": {
      "id": 433,
      "encuentros_fase": 0,
      "shinies": 0,
      "huidos": 0,
      "encuentros_totales": 0,
      "iv_record": {
        "max": -1,
        "min": -1
      },
      "sv_record": {
        "max": -1,
        "min": -1
      }
    },
    "436": {
      "id": 436,
      "encuentros_fase": 0,
      "shinies": 0,
      "huidos": 0,
      "encuentros_totales": 0,
      "iv_record": {
        "max": -1,
        "min": -1
      },
      "sv_record": {
        "max": -1,
        "min": -1
      }
    }
  }
}