{"pokemon":[{
  "movimientos": [
    240,
    16,
    62,
    54
  ],
  "nombre": "Suicune",
  "pid": "adc6fb5e",
  "habilidad": 46,
  "shiny": 0,
  "ivs": {
    "spdef": 26,
    "def": 2,
    "speed": 3,
    "spatt": 30,
    "att": 17,
    "hp": 24
  },
  "nivel": 40,
  "id": 245,
  "genero": 2,
  "sv": 16693
},{
  "movimientos": [
    240,
    16,
    62,
    54
  ],
  "nombre": "Suicune",
  "pid": "549abc0b",
  "habilidad": 46,
  "shiny": 0,
  "ivs": {
    "spdef": 27,
    "def": 15,
    "speed": 18,
    "spatt": 17,
    "att": 15,
    "hp": 24
  },
  "nivel": 40,
  "id": 245,
  "genero": 2,
  "sv": 65340
},{
  "movimientos": [
    240,
    16,
    62,
    54
  ],
  "nombre": "Suicune",
  "pid": "48561fce",
  "habilidad": 46,
  "shiny": 0,
  "ivs": {
    "spdef": 27,
    "def": 15,
    "speed": 0,
    "spatt": 18,
    "att": 7,
    "hp": 4
  },
  "nivel": 40,
  "id": 245,
  "genero": 2,
  "sv": 16437
},{
  "movimientos": [
    240,
    16,
    62,
    54
  ],
  "nombre": "Suicune",
  "pid": "85fc67b2",
  "habilidad": 46,
  "shiny": 0,
  "ivs": {
    "spdef": 15,
    "def": 22,
    "speed": 7,
    "spatt": 26,
    "att": 7,
    "hp": 12
  },
  "nivel": 40,
  "id": 245,
  "genero": 2,
  "sv": 62947
},{
  "movimientos": [
    240,
    16,
    62,
    54
  ],
  "nombre": "Suicune",
  "pid": "ea8a01c8",
  "habilidad": 46,
  "shiny": 0,
  "ivs": {
    "spdef": 20,
    "def": 15,
    "speed": 23,
    "spatt": 3,
    "att": 19,
    "hp": 12
  },
  "nivel": 40,
  "id": 245,
  "genero": 2,
  "sv": 64751
}], "encuentros":27243, "mode":0, "sv_minimo":37}